aiida_codtools/__init__.py
aiida_codtools/calculations/__init__.py
aiida_codtools/calculations/cif_base.py
aiida_codtools/calculations/cif_cell_contents.py
aiida_codtools/calculations/cif_cod_check.py
aiida_codtools/calculations/cif_cod_deposit.py
aiida_codtools/calculations/cif_cod_numbers.py
aiida_codtools/calculations/cif_filter.py
aiida_codtools/calculations/cif_select.py
aiida_codtools/calculations/cif_split_primitive.py
aiida_codtools/calculations/functions/__init__.py
aiida_codtools/calculations/functions/primitive_structure_from_cif.py
aiida_codtools/cli/__init__.py
aiida_codtools/cli/calculations/__init__.py
aiida_codtools/cli/calculations/cod_tools.py
aiida_codtools/cli/data/__init__.py
aiida_codtools/cli/data/cif.py
aiida_codtools/cli/utils/__init__.py
aiida_codtools/cli/utils/display.py
aiida_codtools/cli/utils/launch.py
aiida_codtools/cli/utils/parameters.py
aiida_codtools/cli/utils/validate.py
aiida_codtools/cli/workflows/__init__.py
aiida_codtools/cli/workflows/cif_clean.py
aiida_codtools/common/__init__.py
aiida_codtools/common/resources.py
aiida_codtools/common/utils.py
aiida_codtools/parsers/__init__.py
aiida_codtools/parsers/cif_base.py
aiida_codtools/parsers/cif_cell_contents.py
aiida_codtools/parsers/cif_cod_check.py
aiida_codtools/parsers/cif_cod_deposit.py
aiida_codtools/parsers/cif_cod_numbers.py
aiida_codtools/parsers/cif_split_primitive.py
aiida_codtools/workflows/__init__.py
aiida_codtools/workflows/cif_clean.py
aiida_codtools-3.1.0.dist-info/entry_points.txt
aiida_codtools-3.1.0.dist-info/LICENSE
aiida_codtools-3.1.0.dist-info/WHEEL
aiida_codtools-3.1.0.dist-info/METADATA
aiida_codtools-3.1.0.dist-info/RECORD
