Metadata-Version: 2.1
Name: aiida-codtools
Version: 3.1.0
Summary: The Official AiiDA plugin for the cod-tools package.
Keywords: aiida,workflows
Author-email: The AiiDA team <developers@aiida.net>
Requires-Python: >=3.8
Classifier: Development Status :: 5 - Production/Stable
Classifier: Framework :: AiiDA
Classifier: License :: OSI Approved :: MIT License
Classifier: Programming Language :: Python
Classifier: Programming Language :: Python :: 3.8
Classifier: Programming Language :: Python :: 3.9
Classifier: Programming Language :: Python :: 3.10
Classifier: Programming Language :: Python :: 3.11
Requires-Dist: aiida-core[atomic_tools]~=2.1
Requires-Dist: pgtest~=1.3 ; extra == "dev"
Requires-Dist: pre-commit~=2.17 ; extra == "dev"
Requires-Dist: pylint~=2.16.0 ; extra == "dev"
Requires-Dist: pylint-aiida~=0.1 ; extra == "dev"
Requires-Dist: pytest~=7.0 ; extra == "dev"
Requires-Dist: pytest-regressions~=1.0 ; extra == "dev"
Requires-Dist: toml ; extra == "dev"
Requires-Dist: docutils ; extra == "docs"
Requires-Dist: jinja2>=3.0 ; extra == "docs"
Requires-Dist: sphinx~=4.1 ; extra == "docs"
Requires-Dist: sphinx_rtd_theme ; extra == "docs"
Project-URL: Documentation, https://aiida-codtools.readthedocs.io
Project-URL: Home, https://github.com/aiidateam/aiida-codtools
Project-URL: Source, https://github.com/aiidateam/aiida-codtools
Provides-Extra: dev
Provides-Extra: docs
